pyZynoUnifiedDrivers/__init__.py
pyZynoUnifiedDrivers/visa.py
pyZynoUnifiedDrivers/miva/__init__.py
pyZynoUnifiedDrivers/miva/module_event_log.py
pyZynoUnifiedDrivers/miva/module_infusion.py
pyZynoUnifiedDrivers/miva/module_library.py
pyZynoUnifiedDrivers/miva/module_miva.py
pyZynoUnifiedDrivers/miva/module_motor.py
pyZynoUnifiedDrivers/miva/module_pump.py
pyZynoUnifiedDrivers/miva/module_script.py
pyZynoUnifiedDrivers/miva/module_sendrx.py
pyZynoUnifiedDrivers/miva/module_socket.py
pyZynoUnifiedDrivers/miva/module_socket_server_ssl.py
pyZynoUnifiedDrivers/miva/module_status_monitor.py
pyZynoUnifiedDrivers/miva/module_test.py
pyZynoUnifiedDrivers/miva/module_utils.py
pyZynoUnifiedDrivers-0.0.9.dist-info/LICENSE
pyZynoUnifiedDrivers-0.0.9.dist-info/METADATA
pyZynoUnifiedDrivers-0.0.9.dist-info/WHEEL
pyZynoUnifiedDrivers-0.0.9.dist-info/top_level.txt
pyZynoUnifiedDrivers-0.0.9.dist-info/RECORD
