Metadata-Version: 2.1
Name: pyZynoUnifiedDrivers
Version: 0.0.9
Summary: Zyno Medical Unified Driver: Control your infusion pump with Python
Home-page: https://gitlab.com/liyancen/pyzynounifieddrivers.git
Author: Yancen Li
Author-email: yancen.li@zynomed.com
Classifier: Programming Language :: Python :: 3
Classifier: License :: OSI Approved :: MIT License
Classifier: Operating System :: Microsoft :: Windows
Requires-Python: >=3.7
License-File: LICENSE
Requires-Dist: Pillow
Requires-Dist: pyserial
Requires-Dist: pycryptodomex
